django_blackbox/__init__.py
django_blackbox/activity_tracking.py
django_blackbox/admin.py
django_blackbox/apps.py
django_blackbox/conf.py
django_blackbox/exceptions.py
django_blackbox/helpers.py
django_blackbox/middleware.py
django_blackbox/models.py
django_blackbox/request_id.py
django_blackbox/serializers.py
django_blackbox/services.py
django_blackbox/utils.py
django_blackbox/activity/__init__.py
django_blackbox/activity/decorators.py
django_blackbox/activity/utils.py
django_blackbox/api/__init__.py
django_blackbox/api/permissions.py
django_blackbox/api/serializers.py
django_blackbox/api/urls.py
django_blackbox/api/views.py
django_blackbox/drf/__init__.py
django_blackbox/drf/exception_handler.py
django_blackbox/management/__init__.py
django_blackbox/management/commands/__init__.py
django_blackbox/management/commands/prune_incidents.py
django_blackbox/migrations/0001_initial.py
django_blackbox/migrations/__init__.py
django_blackbox-0.1.3.dist-info/licenses/LICENSE
django_blackbox-0.1.3.dist-info/METADATA
django_blackbox-0.1.3.dist-info/WHEEL
django_blackbox-0.1.3.dist-info/top_level.txt
django_blackbox-0.1.3.dist-info/RECORD
